{
    "type": "object",
    "properties": {
        "maxImageSize": {
            "type": "integer",
            "minimum": 100,
            "maximum": 5000000
        },
        "defaultUserAccess": {
            "$ref": "api://schema/reuse/id.json"
        },
        "maxReservationTime": {
            "type": "integer",
            "minimum": 1
        },
        "minReservationTime": {
            "type": "integer",
            "minimum": 1
        },
        "reservationHistory": {
            "type": "integer",
            "minimum": 1
        },
        "requestHistory": {
            "type": "integer",
            "minimum": 1
        }
    },
    "required": [],
    "additionalProperties": false
}